eyesjrGUI/QtVersion.py
eyesjrGUI/RCtransient.py
eyesjrGUI/RLCsteadystate.py
eyesjrGUI/RLCtransient.py
eyesjrGUI/RLtransient.py
eyesjrGUI/__init__.py
eyesjrGUI/diodeIV.py
eyesjrGUI/driven-pendulum.py
eyesjrGUI/induction.py
eyesjrGUI/language.py
eyesjrGUI/logger.py
eyesjrGUI/main.py
eyesjrGUI/npnCEout.py
eyesjrGUI/pendulumVelocity.py
eyesjrGUI/plotIV.py
eyesjrGUI/rodPendulum.py
eyesjrGUI/scope.py
eyesjrGUI/soundBeats.py
eyesjrGUI/soundFreqResp.py
eyesjrGUI/soundVelocity.py
eyesjrGUI/terminal.py
eyesjrGUI/tof.py
eyesjrGUI/utils.py
eyesjrGUI/eyesjun/__init__.py
eyesjrGUI/eyesjun/eyemath.py
eyesjrGUI/eyesjun/eyes.py
eyesjrGUI/helpFiles/__init__.py
eyesjrGUI/helpFiles/en/1.0.html
eyesjrGUI/helpFiles/en/1.1.html
eyesjrGUI/helpFiles/en/1.2.html
eyesjrGUI/helpFiles/en/1.3.html
eyesjrGUI/helpFiles/en/1.4.html
eyesjrGUI/helpFiles/en/1.5.html
eyesjrGUI/helpFiles/en/2.1.html
eyesjrGUI/helpFiles/en/2.10.html
eyesjrGUI/helpFiles/en/2.11.html
eyesjrGUI/helpFiles/en/2.12.html
eyesjrGUI/helpFiles/en/2.13.html
eyesjrGUI/helpFiles/en/2.14.html
eyesjrGUI/helpFiles/en/2.15.html
eyesjrGUI/helpFiles/en/2.16.html
eyesjrGUI/helpFiles/en/2.17.html
eyesjrGUI/helpFiles/en/2.18.html
eyesjrGUI/helpFiles/en/2.19.html
eyesjrGUI/helpFiles/en/2.2.html
eyesjrGUI/helpFiles/en/2.20.html
eyesjrGUI/helpFiles/en/2.21.html
eyesjrGUI/helpFiles/en/2.3.html
eyesjrGUI/helpFiles/en/2.4.html
eyesjrGUI/helpFiles/en/2.5.html
eyesjrGUI/helpFiles/en/2.6.html
eyesjrGUI/helpFiles/en/2.7.html
eyesjrGUI/helpFiles/en/2.8.html
eyesjrGUI/helpFiles/en/2.9.html
eyesjrGUI/helpFiles/en/3.1.html
eyesjrGUI/helpFiles/en/3.2.html
eyesjrGUI/helpFiles/en/3.3.html
eyesjrGUI/helpFiles/en/3.4.html
eyesjrGUI/helpFiles/en/3.5.html
eyesjrGUI/helpFiles/en/3.6.html
eyesjrGUI/helpFiles/en/3.7.html
eyesjrGUI/helpFiles/en/3.8.html
eyesjrGUI/helpFiles/en/4.1.html
eyesjrGUI/helpFiles/en/4.2.html
eyesjrGUI/helpFiles/en/4.3.html
eyesjrGUI/helpFiles/en/4.4.html
eyesjrGUI/helpFiles/en/4.5.html
eyesjrGUI/helpFiles/en/4.6.html
eyesjr-1.0.1.dist-info/LICENSE
eyesjr-1.0.1.dist-info/METADATA
eyesjr-1.0.1.dist-info/WHEEL
eyesjr-1.0.1.dist-info/entry_points.txt
eyesjr-1.0.1.dist-info/top_level.txt
eyesjr-1.0.1.dist-info/RECORD
