Metadata-Version: 2.1
Name: eyesjr
Version: 1.0.1
Summary: Python package for Expeyesjr
Home-page: https://expeyes.in
Author: Jithin B.P
Author-email: jithinbp@gmail.com
License: UNKNOWN
Project-URL: Source, https://github.com/expeyes/expeyes-programs
Project-URL: Read The Docs, https://expeyes.in
Keywords: expeyesjr data-acquisition lab-at-home oscilloscope waveform-generator sensors physics
Platform: UNKNOWN
Classifier: Development Status :: 5 - Production/Stable
Classifier: Intended Audience :: Education
Classifier: Programming Language :: Python :: 3
Classifier: License :: OSI Approved :: MIT License
Classifier: Operating System :: OS Independent
Requires-Python: >=3
Requires-Dist: PyQt5
Requires-Dist: matplotlib
Requires-Dist: numpy
Requires-Dist: pyqtgraph
Requires-Dist: pyqtwebengine
Requires-Dist: pyserial
Requires-Dist: scipy
